compressed_tensors/__init__.py
compressed_tensors/base.py
compressed_tensors/version.py
compressed_tensors/compressors/__init__.py
compressed_tensors/compressors/base.py
compressed_tensors/compressors/helpers.py
compressed_tensors/compressors/model_compressors/__init__.py
compressed_tensors/compressors/model_compressors/model_compressor.py
compressed_tensors/compressors/quantized_compressors/__init__.py
compressed_tensors/compressors/quantized_compressors/base.py
compressed_tensors/compressors/quantized_compressors/naive_quantized.py
compressed_tensors/compressors/quantized_compressors/pack_quantized.py
compressed_tensors/compressors/sparse_compressors/__init__.py
compressed_tensors/compressors/sparse_compressors/base.py
compressed_tensors/compressors/sparse_compressors/dense.py
compressed_tensors/compressors/sparse_compressors/sparse_24_bitmask.py
compressed_tensors/compressors/sparse_compressors/sparse_bitmask.py
compressed_tensors/compressors/sparse_quantized_compressors/__init__.py
compressed_tensors/compressors/sparse_quantized_compressors/marlin_24.py
compressed_tensors/config/__init__.py
compressed_tensors/config/base.py
compressed_tensors/config/dense.py
compressed_tensors/config/sparse_24_bitmask.py
compressed_tensors/config/sparse_bitmask.py
compressed_tensors/linear/__init__.py
compressed_tensors/linear/compressed_linear.py
compressed_tensors/quantization/__init__.py
compressed_tensors/quantization/quant_args.py
compressed_tensors/quantization/quant_config.py
compressed_tensors/quantization/quant_scheme.py
compressed_tensors/quantization/lifecycle/__init__.py
compressed_tensors/quantization/lifecycle/apply.py
compressed_tensors/quantization/lifecycle/compressed.py
compressed_tensors/quantization/lifecycle/forward.py
compressed_tensors/quantization/lifecycle/helpers.py
compressed_tensors/quantization/lifecycle/initialize.py
compressed_tensors/quantization/utils/__init__.py
compressed_tensors/quantization/utils/helpers.py
compressed_tensors_nightly-0.9.3.20250408.dist-info/licenses/LICENSE
compressed_tensors_nightly-0.9.3.20250408.dist-info/METADATA
compressed_tensors_nightly-0.9.3.20250408.dist-info/WHEEL
compressed_tensors_nightly-0.9.3.20250408.dist-info/top_level.txt
compressed_tensors_nightly-0.9.3.20250408.dist-info/RECORD
